edc_mnsi/__init__.py
edc_mnsi/admin.py
edc_mnsi/admin_site.py
edc_mnsi/apps.py
edc_mnsi/auth_objects.py
edc_mnsi/auths.py
edc_mnsi/calculator.py
edc_mnsi/choices.py
edc_mnsi/factory.py
edc_mnsi/fieldsets.py
edc_mnsi/form_validator.py
edc_mnsi/forms.py
edc_mnsi/list_data.py
edc_mnsi/migrations/0001_initial.py
edc_mnsi/migrations/0002_historicalmnsi_mnsi.py
edc_mnsi/migrations/0003_alter_mnsi_abnormal_obs_left_foot_and_more.py
edc_mnsi/migrations/0004_auto_20220704_1841.py
edc_mnsi/migrations/0005_abnormalfootappearanceobservations_plural_name.py
edc_mnsi/migrations/0006_alter_mnsi_options_alter_mnsi_managers_and_more.py
edc_mnsi/migrations/0007_alter_abnormalfootappearanceobservations_options_and_more.py
edc_mnsi/migrations/0008_alter_historicalmnsi_site_alter_mnsi_site.py
edc_mnsi/migrations/0009_alter_abnormalfootappearanceobservations_extra_value_and_more.py
edc_mnsi/migrations/__init__.py
edc_mnsi/model_admin_mixin.py
edc_mnsi/model_mixins/__init__.py
edc_mnsi/model_mixins/mnsi_model_mixin.py
edc_mnsi/model_mixins/model_fields_mixins.py
edc_mnsi/model_mixins/model_methods_mixins.py
edc_mnsi/models/__init__.py
edc_mnsi/models/list_models.py
edc_mnsi/models/mnsi.py
edc_mnsi/models/signals.py
edc_mnsi/urls.py
edc_mnsi/utils.py
edc_mnsi-1.4.0.dist-info/licenses/LICENSE
edc_mnsi-1.4.0.dist-info/WHEEL
edc_mnsi-1.4.0.dist-info/METADATA
edc_mnsi-1.4.0.dist-info/RECORD
