Metadata-Version: 2.4
Name: edc-mnsi
Version: 1.4.0
Summary: MNSI form/model for the clinicedc/edc and other django projects
Keywords: clinical,clinicedc,django,edc,mnsi,trials
Author: Jonathan Willitts
Author-email: Jonathan Willitts <Jonathan.Willitts@lstmed.ac.uk>
License-Expression: GPL-3.0-or-later
License-File: LICENSE
Classifier: Development Status :: 5 - Production/Stable
Classifier: Framework :: Django
Classifier: Framework :: Django :: 5.2
Classifier: Intended Audience :: Developers
Classifier: Intended Audience :: Science/Research
Classifier: License :: OSI Approved :: GNU General Public License v3 (GPLv3)
Classifier: Operating System :: OS Independent
Classifier: Programming Language :: Python :: 3.12
Classifier: Programming Language :: Python :: 3.13
Requires-Dist: clinicedc>=2.1.0
Requires-Python: >=3.12, <3.14
Project-URL: Homepage, https://github.com/clinicedc/edc-mnsi
